jcx/__init__.py
jcx/api/__init__.py
jcx/api/command.py
jcx/api/config.py
jcx/api/dao_item.py
jcx/api/dao_list.py
jcx/bin/cx_cp.py
jcx/bin/cx_cvt.py
jcx/bin/cx_dir_cmp.py
jcx/bin/cx_find.py
jcx/bin/cx_fst.py
jcx/bin/cx_hisotry_clean.py
jcx/bin/cx_ref_pick.py
jcx/bin/cx_rename.py
jcx/bin/cx_unpack.py
jcx/bin/mv_re.py
jcx/bin/rename_re.py
jcx/common.py
jcx/data/__init__.py
jcx/data/split.py
jcx/db/__init__.py
jcx/db/counter.py
jcx/db/ivariant.py
jcx/db/jdb/__init__.py
jcx/db/jdb/counter.py
jcx/db/jdb/table.py
jcx/db/jdb/util.py
jcx/db/jdb/variant.py
jcx/db/rdb/__init__.py
jcx/db/rdb/counter.py
jcx/db/rdb/db.py
jcx/db/rdb/mutithread.py
jcx/db/rdb/variant.py
jcx/db/record.py
jcx/m/__init__.py
jcx/m/average_meter.py
jcx/m/fun.py
jcx/m/number.py
jcx/m/rand.py
jcx/m/sqrt.py
jcx/m/trace.py
jcx/net/__init__.py
jcx/net/mqtt/README.md
jcx/net/mqtt/__init__.py
jcx/net/mqtt/cfg.py
jcx/net/mqtt/mqtt_c.py
jcx/net/mqtt/mqtt_s.py
jcx/net/mqtt/publisher.py
jcx/net/mqtt/subscriber.py
jcx/py.typed
jcx/rs/__init__.py
jcx/rs/proto.py
jcx/rs/rs.py
jcx/sys/__init__.py
jcx/sys/fs.py
jcx/text/__init__.py
jcx/text/io.py
jcx/text/txt_json.py
jcx/time/__init__.py
jcx/time/calendar_type.py
jcx/time/clock_time.py
jcx/time/count_timer.py
jcx/time/dt.py
jcx/time/timer.py
jcx/ui/__init__.py
jcx/ui/key.py
jcx/ui/progress_meter.py
jcx/util/__init__.py
jcx/util/algo.py
jcx/util/array.py
jcx/util/err.py
jcx/util/lict.py
jcx/util/mutithread.py
jcx/util/oo.py
jcx/util/trace.py
jcx-0.4.0.dist-info/LICENSE
jcx-0.4.0.dist-info/METADATA
jcx-0.4.0.dist-info/WHEEL
jcx-0.4.0.dist-info/RECORD
