Metadata-Version: 2.3
Name: jcx
Version: 0.4.0
Summary: 
Author: dayn9t
Author-email: dayn9t@gmail.com
Requires-Python: ~=3.12
Classifier: Programming Language :: Python :: 3
Classifier: Programming Language :: Python :: 3.12
Classifier: Programming Language :: Python :: 3.13
Requires-Dist: arrow
Requires-Dist: interval
Requires-Dist: loguru
Requires-Dist: numpy
Requires-Dist: paho-mqtt
Requires-Dist: parse
Requires-Dist: pre-commit
Requires-Dist: pydantic
Requires-Dist: redis
Requires-Dist: requests
Requires-Dist: rustshed
Requires-Dist: sh
Requires-Dist: typer
Requires-Dist: types-paho-mqtt
